shc/__init__.py
shc/base.py
shc/conversion.py
shc/data_logging.py
shc/datatypes.py
shc/expressions.py
shc/misc.py
shc/py.typed
shc/supervisor.py
shc/timer.py
shc/variables.py
shc/interfaces/__init__.py
shc/interfaces/_helper.py
shc/interfaces/_pulse_ffi.py
shc/interfaces/command.py
shc/interfaces/dmx.py
shc/interfaces/file_persistence.py
shc/interfaces/in_memory_data_logging.py
shc/interfaces/knx.py
shc/interfaces/midi.py
shc/interfaces/mqtt.py
shc/interfaces/mysql.py
shc/interfaces/ping.py
shc/interfaces/pulse.py
shc/interfaces/shc_client.py
shc/interfaces/system_monitoring.py
shc/interfaces/tasmota.py
shc/interfaces/telegram.py
shc/util/__init__.py
shc/util/check_shc.py
shc/util/mypy_variable_plugin.py
shc/web/__init__.py
shc/web/interface.py
shc/web/log_widgets.py
shc/web/widgets.py
shc/web/static/apple-touch-icon.png
shc/web/static/favicon.ico
shc/web/static/pack/Lato-Bold.367f6330.woff
shc/web/static/pack/Lato-Bold.b0c7a5bb.woff2
shc/web/static/pack/Lato-BoldItalic.86b3f184.woff2
shc/web/static/pack/Lato-BoldItalic.a844a9b2.woff
shc/web/static/pack/Lato-Italic.c1782172.woff2
shc/web/static/pack/Lato-Italic.eab68376.woff
shc/web/static/pack/Lato-Regular.96b82b78.woff
shc/web/static/pack/Lato-Regular.ebc7de56.woff2
shc/web/static/pack/LatoLatin-Bold.8431ae36.woff2
shc/web/static/pack/LatoLatin-Bold.c7218d37.woff
shc/web/static/pack/LatoLatin-BoldItalic.26f6ffbc.woff
shc/web/static/pack/LatoLatin-BoldItalic.a8e39bbd.woff2
shc/web/static/pack/LatoLatin-Italic.d2089e8b.woff2
shc/web/static/pack/LatoLatin-Italic.de0574c8.woff
shc/web/static/pack/LatoLatin-Regular.a124b19d.woff
shc/web/static/pack/LatoLatin-Regular.b321314c.woff2
shc/web/static/pack/brand-icons.0b52c614.woff2
shc/web/static/pack/brand-icons.a0b02584.woff
shc/web/static/pack/icons.6002b354.woff2
shc/web/static/pack/icons.80005ece.woff
shc/web/static/pack/main.css
shc/web/static/pack/main.css.map
shc/web/static/pack/main.js
shc/web/static/pack/main.js.map
shc/web/static/pack/outline-icons.09c79cc5.woff
smarthomeconnect-0.9.0.dist-info/LICENSE
smarthomeconnect-0.9.0.dist-info/METADATA
smarthomeconnect-0.9.0.dist-info/NOTICE
smarthomeconnect-0.9.0.dist-info/WHEEL
smarthomeconnect-0.9.0.dist-info/top_level.txt
smarthomeconnect-0.9.0.dist-info/RECORD
