Metadata-Version: 2.1
Name: smarthomeconnect
Version: 0.9.0
Summary: The Smart Home Connect home automation framework based on AsyncIO
Home-page: https://github.com/mhthies/smarthomeconnect
Author: Michael Thies
Author-email: mail@mhthies.de
License: Apache License 2.0
Project-URL: Documentation, https://smarthomeconnect.readthedocs.org/
Project-URL: Source, https://github.com/mhthies/smarthomeconnect
Project-URL: Tracker, https://github.com/mhthies/smarthomeconnect/issues
Classifier: Development Status :: 4 - Beta
Classifier: Programming Language :: Python :: 3.8
Classifier: Programming Language :: Python :: 3.9
Classifier: Programming Language :: Python :: 3.10
Classifier: Programming Language :: Python :: 3.11
Classifier: Programming Language :: Python :: 3.12
Classifier: License :: OSI Approved :: Apache Software License
Classifier: Topic :: Home Automation
Classifier: Framework :: AsyncIO
Requires-Python: ~=3.7
License-File: NOTICE
License-File: LICENSE
Requires-Dist: aiohttp<4,>=3.6
Requires-Dist: jinja2<4,>=2.11
Requires-Dist: MarkupSafe<3,>=1.1
Provides-Extra: dmx
Requires-Dist: pyserial-asyncio<0.7,>=0.3; extra == "dmx"
Provides-Extra: file_persistence
Requires-Dist: aiofile<4,>=3.7.4; extra == "file-persistence"
Provides-Extra: knx
Requires-Dist: knxdclient<2,>=0.4.0; extra == "knx"
Provides-Extra: midi
Requires-Dist: mido<2,>=1.2.9; extra == "midi"
Requires-Dist: python-rtmidi<2,>=1.4.6; extra == "midi"
Provides-Extra: mqtt
Requires-Dist: aiomqtt<3,>=2.0.0; extra == "mqtt"
Provides-Extra: mysql
Requires-Dist: aiomqtt<3,>=2.0.0; extra == "mysql"
Provides-Extra: pulse
Requires-Dist: pulsectl-asyncio<2,>=1.0.0; extra == "pulse"
Provides-Extra: telegram
Requires-Dist: aiogram<4,>=3.0; extra == "telegram"
